LICENSE
MANIFEST.in
README.md
VERSION
setup.cfg
setup.py
graph_service_framework/__init__.py
graph_service_framework/conftest.py
graph_service_framework/query.graphql
graph_service_framework/schema.py
graph_service_framework/schema_tracker.py
graph_service_framework/service.py
graph_service_framework/service_manager.py
graph_service_framework/service_manager_middleware.py
graph_service_framework/utils.py
graph_service_framework.egg-info/PKG-INFO
graph_service_framework.egg-info/SOURCES.txt
graph_service_framework.egg-info/dependency_links.txt
graph_service_framework.egg-info/requires.txt
graph_service_framework.egg-info/top_level.txt
tests/__init__.py
tests/test_dispatcher.py
tests/test_schema.py
tests/test_service.py
tests/test_service_manager.py
tests/utils.py