Metadata-Version: 2.1
Name: graph-service-framework
Version: 1.1.53
Summary: GraphQL Service Framework.
Home-page: https://gitlab.com/parob/graph-service-framework
Download-URL: https://gitlab.com/parob/graph-service-framework/-/archive/master/graph-service-framework-v1.1.53.zip
Author: Robert Parker
Author-email: rob@parob.com
License: MIT
Keywords: GraphQL
Classifier: Development Status :: 3 - Alpha
Classifier: Intended Audience :: Developers
Classifier: Programming Language :: Python :: 3
Classifier: License :: OSI Approved :: MIT License
Classifier: Operating System :: OS Independent
License-File: LICENSE
